automl/__init__.py
automl/core.py
automl/evaluator.py
automl/explainer.py
automl/models.py
automl/preprocess.py
automl/utils.py
automl/visualizer.py
mlsherpa-0.1.1.dist-info/licenses/LICENSE
tests/test_automl.py
tests/test_core.py
mlsherpa-0.1.1.dist-info/METADATA
mlsherpa-0.1.1.dist-info/WHEEL
mlsherpa-0.1.1.dist-info/top_level.txt
mlsherpa-0.1.1.dist-info/RECORD
