Metadata-Version: 2.4
Name: mlsherpa
Version: 0.1.1
Summary: A lightweight AutoML framework
Author-email: Tanmai Raghava <your.email@example.com>
License: MIT
Classifier: Programming Language :: Python :: 3
Classifier: License :: OSI Approved :: MIT License
Classifier: Operating System :: OS Independent
Requires-Python: >=3.7
License-File: LICENSE
Requires-Dist: numpy
Requires-Dist: pandas
Requires-Dist: scikit-learn
Requires-Dist: matplotlib
Requires-Dist: seaborn
Provides-Extra: dev
Requires-Dist: pytest; extra == "dev"
Dynamic: license-file
